LICENSE
MANIFEST.in
README
setup.py
ent/__init__.py
ent/ent.py
ent/json.py
ent/yaml.py
ent.egg-info/PKG-INFO
ent.egg-info/SOURCES.txt
ent.egg-info/dependency_links.txt
ent.egg-info/requires.txt
ent.egg-info/top_level.txt