Metadata-Version: 1.1
Name: ent
Version: 0.3.2
Summary: library for creating arbitrary data structures
Home-page: https://github.com/jreese/ent
Author: John Reese
Author-email: john@noswap.com
License: MIT License
Platform: UNKNOWN
Classifier: License :: OSI Approved :: MIT License
Classifier: Programming Language :: Python
Classifier: Programming Language :: Python :: 2.7
Classifier: Programming Language :: Python :: 3
Classifier: Programming Language :: Python :: 3.3
Classifier: Programming Language :: Python :: 3.4
Classifier: Topic :: Software Development :: Libraries
Classifier: Development Status :: 3 - Alpha
